{
	"schemaVersion": 1,
	"id": "inordinate",
	"version": "${version}",
	"name": "Inordinate",
	"description": "This is a clutter mod! Tell everyone about it!",
	"authors": [
		"Antonic!"
	],
	"contact": {
		"homepage": "https://fabricmc.net/",
		"sources": "https://github.com/FabricMC/fabric-example-mod"
	},
	"license": "MIT",
	"icon": "assets/inordinate/icon.png",
	"environment": "*",
	"entrypoints": {
		"fabric-datagen": [
      		"com.antonic.inordinate.datagen.DataGeneration"
    	],
		"main": [
			"com.antonic.inordinate.InordinateMod"
		],
		"client": [
			"com.antonic.inordinate.InordinateModClient"
		],
		"mixins": [
			"inordinate.mixins.json"
		]
	},
	"depends": {
		"fabricloader": ">=0.14.22",
		"minecraft": "~1.20.2",
		"java": ">=17",
		"fabric-api": "*"
	},
	"suggests": {
		"another-mod": "*"
	}
}
